{
  "100": "waddling in the town",
  "110": "drinking coffee",
  "111": "reading books",
  "120": "dancing at the night club",
  "121": "playing arcade games",
  "122": "school",
  "130": "shopping",
  "200": "",
  "210": "",
  "212": "agentlobbymulti",
  "213": "in a staff meeting",
  "220": "relaxing at the lodge",
  "221": "poking through the attic",
  "230": "on top of the mountain",
  "300": "hanging out at the plaza",
  "310": "looking at puffles",
  "320": "hiding in the dojo",
  "321": "cheating",
  "323": "cheating",
  "324": "cheating",
  "326": "cheating",
  "330": "eating pizza",
  "340": "cheating",
  "400": "sunbathing at the beach",
  "410": "playing at the lighthouse",
  "411": "admiring the skyline",
  "420": "boarding the migrator",
  "421": "shopping in the ship hold",
  "422": "looking around the quarters",
  "423": "watching from the crow's nest",
  "430": "hotellobby",
  "431": "hotelspa",
  "432": "hotelroof",
  "433": "cloudforest",
  "434": "park",
  "435": "skatepark",
  "436": "pufflewild",
  "437": "ufo",
  "800": "working at the dock",
  "801": "throwing snowballs",
  "802": "playing ice hockey",
  "803": "on classified business",
  "804": "reading old news",
  "805": "tipping the iceberg",
  "806": "swimming",
  "807": "outside the mine",
  "808": "throwing rocks in the mine",
  "809": "enjoying the wilderness",
  "810": "surfing at the Cove",
  "811": "in another dimension",
  "812": "cheating",
  "813": "???",
  "814": "???",
  "815": "???",
  "816": "dojowater",
  "851": "party1",
  "852": "party2",
  "853": "party3",
  "854": "party4",
  "855": "party5",
  "856": "party6",
  "857": "party7",
  "858": "party8",
  "859": "party9",
  "860": "party10",
  "861": "party11",
  "862": "party12",
  "863": "party13",
  "864": "party14",
  "865": "party15",
  "866": "party16",
  "867": "party17",
  "868": "party18",
  "869": "party19",
  "874": "party24",
  "875": "party25",
  "876": "party26",
  "877": "party27",
  "878": "party28",
  "890": "party99",
  "891": "partysolo1",
  "898": "soundroom",
  "899": "party",
  "900": "playing astro barrier",
  "901": "playing bean counters",
  "902": "catching puffles",
  "903": "playing ballistic biscuit",
  "904": "catching fish",
  "905": "Cart Surfing",
  "906": "flying a jet pack",
  "907": "on agent business",
  "908": "on agent business",
  "909": "playing thin ice",
  "910": "making pizzas",
  "911": "on agent business",
  "912": "surfing",
  "913": "on agent business",
  "914": "on agent business",
  "915": "on agent business",
  "916": "playing Aqua Grabber",
  "917": "playing Paint By Letters",
  "918": "playing Paint By Letters",
  "919": "playing Paint By Letters",
  "920": "on agent business",
  "921": "on agent business",
  "922": "on agent business",
  "923": "on agent business",
  "924": "",
  "925": "",
  "926": "mixing music",
  "927": "on agent business",
  "941": "winning tickets",
  "942": "winning tickets",
  "943": "winning tickets",
  "944": "winning tickets",
  "945": "winning tickets",
  "946": "winning tickets",
  "947": "winning tickets",
  "948": "winning tickets",
  "949": "rescuing puffles",
  "950": "playing system defender",
  "951": "playing card-jitsu",
  "952": "in a dance contest",
  "953": "playing card-jitsu Fire",
  "954": "playing card-jitsu Water",
  "955": "watching fluffy",
  "956": "playing pizza oven",
  "957": "",
  "958": "",
  "959": "",
  "960": "",
  "961": "",
  "962": "partygame",
  "963": "",
  "994": "",
  "995": "",
  "996": "",
  "997": "",
  "998": "",
  "999": "party19",
  "1100": "",
  "1104": "???"
}